bangla_postagger/__init__.py
bangla_postagger/bn_en_mapper.py
bangla_postagger/en_postaggers.py
bangla_postagger/translators.py
bangla_postagger-0.13.0.dist-info/WHEEL
bangla_postagger-0.13.0.dist-info/METADATA
bangla_postagger-0.13.0.dist-info/RECORD
