Metadata-Version: 2.1
Name: bangla-postagger
Version: 0.13.0
Summary: A Bangla Parts of Speech Tagger using Bangla-English Alignment
Home-page: https://github.com/MusfiqDehan/bangla-postagger
License: MIT
Keywords: nlp,data-preprocessors,data-preprocessing,text-preprocessing,data-science,bangla-pos-tagger,musfiqdehan
Author: Md. Musfiqur Rahaman
Author-email: musfiqur.rahaman@northsouth.edu
Requires-Python: >=3.7.1,<4.0.0
Classifier: Development Status :: 5 - Production/Stable
Classifier: Intended Audience :: Developers
Classifier: Intended Audience :: Education
Classifier: Intended Audience :: Information Technology
Classifier: License :: OSI Approved :: MIT License
Classifier: Operating System :: OS Independent
Classifier: Programming Language :: Python :: 3
Classifier: Programming Language :: Python :: 3.10
Classifier: Programming Language :: Python :: 3.8
Classifier: Programming Language :: Python :: 3.9
Classifier: Topic :: Communications
Classifier: Topic :: Education
Classifier: Topic :: Software Development
Classifier: Topic :: Text Processing
Classifier: Topic :: Text Processing :: Linguistic
Requires-Dist: deep-translator (>=1.8.3,<2.0.0)
Requires-Dist: flair (>=0.11.1,<0.12.0)
Requires-Dist: spacy (>=3.3.0,<4.0.0)
Requires-Dist: textblob (>=0.17.1,<0.18.0)
Requires-Dist: torch (>=1.11.0,<2.0.0)
Project-URL: Repository, https://github.com/MusfiqDehan/bangla-postagger
